kiara_modules/language_processing/__init__.py
kiara_modules/language_processing/lda.py
kiara_modules/language_processing/lemmatize.py
kiara_modules/language_processing/metadata_schemas.py
kiara_modules/language_processing/py.typed
kiara_modules/language_processing/tokens.py
kiara_modules/language_processing/value_types.py
kiara_modules/language_processing/pipelines/.gitkeep
kiara_modules/language_processing/pipelines/__init__.py
kiara_modules/language_processing/resources/.gitkeep
kiara_modules.language_processing-0.3.0.dist-info/LICENSE
kiara_modules.language_processing-0.3.0.dist-info/METADATA
kiara_modules.language_processing-0.3.0.dist-info/WHEEL
kiara_modules.language_processing-0.3.0.dist-info/entry_points.txt
kiara_modules.language_processing-0.3.0.dist-info/top_level.txt
kiara_modules.language_processing-0.3.0.dist-info/RECORD
